{"id":310,"name":"Manectric","moves":[{"name":"Agility","type":"psychic"},{"name":"Attract","type":"normal"},{"name":"Bite","type":"dark"},{"name":"Body Slam","type":"normal"},{"name":"Captivate","type":"normal"},{"name":"Charge","type":"electric"},{"name":"Charge Beam","type":"electric"},{"name":"Confide","type":"normal"},{"name":"Crunch","type":"dark"},{"name":"Discharge","type":"electric"},{"name":"Double Team","type":"normal"},{"name":"Double-Edge","type":"normal"},{"name":"Eerie Impulse","type":"electric"},{"name":"Electric Terrain","type":"electric"},{"name":"Electro Ball","type":"electric"},{"name":"Endure","type":"normal"},{"name":"Facade","type":"normal"},{"name":"Fire Fang","type":"fire"},{"name":"Flamethrower","type":"fire"},{"name":"Flash","type":"normal"},{"name":"Frustration","type":"normal"},{"name":"Giga Impact","type":"normal"},{"name":"Headbutt","type":"normal"},{"name":"Hidden Power","type":"normal"},{"name":"Howl","type":"normal"},{"name":"Hyper Beam","type":"normal"},{"name":"Hyper Voice","type":"normal"},{"name":"Ice Fang","type":"ice"},{"name":"Iron Tail","type":"steel"},{"name":"Laser Focus","type":"normal"},{"name":"Leer","type":"normal"},{"name":"Light Screen","type":"psychic"},{"name":"Magnet Rise","type":"electric"},{"name":"Mimic","type":"normal"},{"name":"Mud-Slap","type":"ground"},{"name":"Natural Gift","type":"normal"},{"name":"Odor Sleuth","type":"normal"},{"name":"Overheat","type":"fire"},{"name":"Protect","type":"normal"},{"name":"Psychic Fangs","type":"psychic"},{"name":"Quick Attack","type":"normal"},{"name":"Rain Dance","type":"water"},{"name":"Refresh","type":"normal"},{"name":"Rest","type":"psychic"},{"name":"Return","type":"normal"},{"name":"Rising Voltage","type":"electric"},{"name":"Roar","type":"normal"},{"name":"Round","type":"normal"},{"name":"Scary Face","type":"normal"},{"name":"Secret Power","type":"normal"},{"name":"Shock Wave","type":"electric"},{"name":"Signal Beam","type":"bug"},{"name":"Sleep Talk","type":"normal"},{"name":"Snarl","type":"dark"},{"name":"Snore","type":"normal"},{"name":"Spark","type":"electric"},{"name":"Strength","type":"normal"},{"name":"Substitute","type":"normal"},{"name":"Swagger","type":"normal"},{"name":"Swift","type":"normal"},{"name":"Tackle","type":"normal"},{"name":"Thief","type":"dark"},{"name":"Thunder","type":"electric"},{"name":"Thunder Fang","type":"electric"},{"name":"Thunder Wave","type":"electric"},{"name":"Thunderbolt","type":"electric"},{"name":"Toxic","type":"poison"},{"name":"Uproar","type":"normal"},{"name":"Volt Switch","type":"electric"},{"name":"Wild Charge","type":"electric"}],"types":["electric"],"evolutions":[{"name":"Electrike","id":309},{"name":"Manectric","id":310}],"abilities":["Lightning Rod","Minus","Static"]}