{"id":535,"name":"Tympole","moves":[{"name":"Acid","type":"poison"},{"name":"After You","type":"normal"},{"name":"Aqua Ring","type":"water"},{"name":"Attract","type":"normal"},{"name":"Bounce","type":"flying"},{"name":"Bubble","type":"water"},{"name":"Bubble Beam","type":"water"},{"name":"Confide","type":"normal"},{"name":"Double Team","type":"normal"},{"name":"Earth Power","type":"ground"},{"name":"Echoed Voice","type":"normal"},{"name":"Endeavor","type":"normal"},{"name":"Endure","type":"normal"},{"name":"Facade","type":"normal"},{"name":"Flail","type":"normal"},{"name":"Frustration","type":"normal"},{"name":"Growl","type":"normal"},{"name":"Hail","type":"ice"},{"name":"Hidden Power","type":"normal"},{"name":"Hydro Pump","type":"water"},{"name":"Hyper Voice","type":"normal"},{"name":"Icy Wind","type":"ice"},{"name":"Infestation","type":"bug"},{"name":"Mist","type":"ice"},{"name":"Mud Bomb","type":"ground"},{"name":"Mud Shot","type":"ground"},{"name":"Mud Sport","type":"ground"},{"name":"Mud-Slap","type":"ground"},{"name":"Muddy Water","type":"water"},{"name":"Protect","type":"normal"},{"name":"Rain Dance","type":"water"},{"name":"Refresh","type":"normal"},{"name":"Rest","type":"psychic"},{"name":"Return","type":"normal"},{"name":"Round","type":"normal"},{"name":"Scald","type":"water"},{"name":"Screech","type":"normal"},{"name":"Secret Power","type":"normal"},{"name":"Sleep Talk","type":"normal"},{"name":"Sludge Bomb","type":"poison"},{"name":"Sludge Wave","type":"poison"},{"name":"Snore","type":"normal"},{"name":"Substitute","type":"normal"},{"name":"Supersonic","type":"normal"},{"name":"Surf","type":"water"},{"name":"Swagger","type":"normal"},{"name":"Toxic","type":"poison"},{"name":"Uproar","type":"normal"},{"name":"Venom Drench","type":"poison"},{"name":"Water Pulse","type":"water"},{"name":"Weather Ball","type":"normal"}],"types":["water"],"evolutions":[{"name":"Tympole","id":535}],"abilities":["Hydration","Swift Swim","Water Absorb"]}