{"id":942,"name":"Maschiff","moves":[{"name":"Bite","type":"dark"},{"name":"Body Slam","type":"normal"},{"name":"Charm","type":"fairy"},{"name":"Crunch","type":"dark"},{"name":"Dark Pulse","type":"dark"},{"name":"Destiny Bond","type":"ghost"},{"name":"Dig","type":"ground"},{"name":"Double-Edge","type":"normal"},{"name":"Endeavor","type":"normal"},{"name":"Endure","type":"normal"},{"name":"Facade","type":"normal"},{"name":"Fake Tears","type":"dark"},{"name":"Fire Fang","type":"fire"},{"name":"Headbutt","type":"normal"},{"name":"Helping Hand","type":"normal"},{"name":"Hone Claws","type":"dark"},{"name":"Ice Fang","type":"ice"},{"name":"Jaw Lock","type":"dark"},{"name":"Leer","type":"normal"},{"name":"Lick","type":"ghost"},{"name":"Payback","type":"dark"},{"name":"Play Rough","type":"fairy"},{"name":"Protect","type":"normal"},{"name":"Psychic Fangs","type":"psychic"},{"name":"Rain Dance","type":"water"},{"name":"Rest","type":"psychic"},{"name":"Retaliate","type":"normal"},{"name":"Reversal","type":"fighting"},{"name":"Roar","type":"normal"},{"name":"Scary Face","type":"normal"},{"name":"Sleep Talk","type":"normal"},{"name":"Snarl","type":"dark"},{"name":"Substitute","type":"normal"},{"name":"Sunny Day","type":"fire"},{"name":"Swagger","type":"normal"},{"name":"Tackle","type":"normal"},{"name":"Take Down","type":"normal"},{"name":"Taunt","type":"dark"},{"name":"Tera Blast","type":"normal"},{"name":"Thief","type":"dark"},{"name":"Thunder Fang","type":"electric"},{"name":"Trailblaze","type":"grass"}],"types":["dark"],"evolutions":[{"name":"Maschiff","id":942}],"abilities":["Intimidate","Run Away","Stakeout"]}