[{"name":"Abomasnow","id":460},{"name":"Abra","id":63},{"name":"Absol","id":359},{"name":"Accelgor","id":617},{"name":"Aegislash","id":681},{"name":"Aegislash Blade","id":10026},{"name":"Aerodactyl","id":142},{"name":"Aggron","id":306},{"name":"Aipom","id":190},{"name":"Alakazam","id":65},{"name":"Alcremie","id":869},{"name":"Alomomola","id":594},{"name":"Altaria","id":334},{"name":"Amaura","id":698},{"name":"Ambipom","id":424},{"name":"Amoonguss","id":591},{"name":"Ampharos","id":181},{"name":"Annihilape","id":979},{"name":"Anorith","id":347},{"name":"Appletun","id":842},{"name":"Applin","id":840},{"name":"Araquanid","id":752},{"name":"Arbok","id":24},{"name":"Arboliva","id":930},{"name":"Arcanine","id":59},{"name":"Arcanine Hisui","id":10230},{"name":"Arceus","id":493},{"name":"Arceus Bug","id":493},{"name":"Arceus Dark","id":493},{"name":"Arceus Dragon","id":493},{"name":"Arceus Electric","id":493},{"name":"Arceus Fairy","id":493},{"name":"Arceus Fighting","id":493},{"name":"Arceus Fire","id":493},{"name":"Arceus Flying","id":493},{"name":"Arceus Ghost","id":493},{"name":"Arceus Grass","id":493},{"name":"Arceus Ground","id":493},{"name":"Arceus Ice","id":493},{"name":"Arceus Poison","id":493},{"name":"Arceus Psychic","id":493},{"name":"Arceus Rock","id":493},{"name":"Arceus Steel","id":493},{"name":"Arceus Water","id":493},{"name":"Archen","id":566},{"name":"Archeops","id":567},{"name":"Arctibax","id":997},{"name":"Arctovish","id":883},{"name":"Arctozolt","id":881},{"name":"Ariados","id":168},{"name":"Armaldo","id":348},{"name":"Armarouge","id":936},{"name":"Aromatisse","id":683},{"name":"Aron","id":304},{"name":"Arrokuda","id":846},{"name":"Articuno","id":144},{"name":"Articuno Galar","id":10169},{"name":"Audino","id":531},{"name":"Aurorus","id":699},{"name":"Avalugg","id":713},{"name":"Avalugg Hisui","id":10243},{"name":"Axew","id":610},{"name":"Azelf","id":482},{"name":"Azumarill","id":184},{"name":"Azurill","id":298},{"name":"Bagon","id":371},{"name":"Baltoy","id":343},{"name":"Banette","id":354},{"name":"Barbaracle","id":689},{"name":"Barboach","id":339},{"name":"Barraskewda","id":847},{"name":"Basculegion","id":902},{"name":"Basculin","id":550},{"name":"Basculin Blue Striped","id":10016},{"name":"Basculin White Striped","id":10247},{"name":"Bastiodon","id":411},{"name":"Baxcalibur","id":998},{"name":"Bayleef","id":153},{"name":"Beartic","id":614},{"name":"Beautifly","id":267},{"name":"Beedrill","id":15},{"name":"Beheeyem","id":606},{"name":"Beldum","id":374},{"name":"Bellibolt","id":939},{"name":"Bellossom","id":182},{"name":"Bellsprout","id":69},{"name":"Bergmite","id":712},{"name":"Bewear","id":760},{"name":"Bibarel","id":400},{"name":"Bidoof","id":399},{"name":"Binacle","id":688},{"name":"Bisharp","id":625},{"name":"Blacephalon","id":806},{"name":"Blastoise","id":9},{"name":"Blaziken","id":257},{"name":"Blipbug","id":824},{"name":"Blissey","id":242},{"name":"Blitzle","id":522},{"name":"Boldore","id":525},{"name":"Boltund","id":836},{"name":"Bombirdier","id":962},{"name":"Bonsly","id":438},{"name":"Bouffalant","id":626},{"name":"Bounsweet","id":761},{"name":"Braixen","id":654},{"name":"Brambleghast","id":947},{"name":"Bramblin","id":946},{"name":"Braviary","id":628},{"name":"Braviary Hisui","id":10240},{"name":"Breloom","id":286},{"name":"Brionne","id":729},{"name":"Bronzong","id":437},{"name":"Bronzor","id":436},{"name":"Brute Bonnet","id":986},{"name":"Bruxish","id":779},{"name":"Budew","id":406},{"name":"Buizel","id":418},{"name":"Bulbasaur","id":1},{"name":"Buneary","id":427},{"name":"Bunnelby","id":659},{"name":"Burmy","id":412},{"name":"Butterfree","id":12},{"name":"Buzzwole","id":794},{"name":"Cacnea","id":331},{"name":"Cacturne","id":332},{"name":"Calyrex","id":898},{"name":"Calyrex Ice","id":10193},{"name":"Calyrex Shadow","id":10194},{"name":"Camerupt","id":323},{"name":"Capsakid","id":951},{"name":"Carbink","id":703},{"name":"Carkol","id":838},{"name":"Carnivine","id":455},{"name":"Carracosta","id":565},{"name":"Carvanha","id":318},{"name":"Cascoon","id":268},{"name":"Castform","id":351},{"name":"Castform Rainy","id":10014},{"name":"Castform Snowy","id":10015},{"name":"Castform Sunny","id":10013},{"name":"Caterpie","id":10},{"name":"Celebi","id":251},{"name":"Celesteela","id":797},{"name":"Centiskorch","id":851},{"name":"Ceruledge","id":937},{"name":"Cetitan","id":975},{"name":"Cetoddle","id":974},{"name":"Chandelure","id":609},{"name":"Chansey","id":113},{"name":"Charcadet","id":935},{"name":"Charizard","id":6},{"name":"Charjabug","id":737},{"name":"Charmander","id":4},{"name":"Charmeleon","id":5},{"name":"Chatot","id":441},{"name":"Cherrim","id":421},{"name":"Cherubi","id":420},{"name":"Chesnaught","id":652},{"name":"Chespin","id":650},{"name":"Chewtle","id":833},{"name":"Chi Yu","id":1004},{"name":"Chien Pao","id":1002},{"name":"Chikorita","id":152},{"name":"Chimchar","id":390},{"name":"Chimecho","id":358},{"name":"Chinchou","id":170},{"name":"Chingling","id":433},{"name":"Cinccino","id":573},{"name":"Cinderace","id":815},{"name":"Clamperl","id":366},{"name":"Clauncher","id":692},{"name":"Clawitzer","id":693},{"name":"Claydol","id":344},{"name":"Clefable","id":36},{"name":"Clefairy","id":35},{"name":"Cleffa","id":173},{"name":"Clobbopus","id":852},{"name":"Clodsire","id":980},{"name":"Cloyster","id":91},{"name":"Coalossal","id":839},{"name":"Cobalion","id":638},{"name":"Cofagrigus","id":563},{"name":"Combee","id":415},{"name":"Combusken","id":256},{"name":"Comfey","id":764},{"name":"Conkeldurr","id":534},{"name":"Copperajah","id":879},{"name":"Corphish","id":341},{"name":"Corsola","id":222},{"name":"Corsola Galar","id":10173},{"name":"Corviknight","id":823},{"name":"Corvisquire","id":822},{"name":"Cosmoem","id":790},{"name":"Cosmog","id":789},{"name":"Cottonee","id":546},{"name":"Crabominable","id":740},{"name":"Crabrawler","id":739},{"name":"Cradily","id":346},{"name":"Cramorant","id":845},{"name":"Cranidos","id":408},{"name":"Crawdaunt","id":342},{"name":"Cresselia","id":488},{"name":"Croagunk","id":453},{"name":"Crobat","id":169},{"name":"Crocalor","id":910},{"name":"Croconaw","id":159},{"name":"Crustle","id":558},{"name":"Cryogonal","id":615},{"name":"Cubchoo","id":613},{"name":"Cubone","id":104},{"name":"Cufant","id":878},{"name":"Cursola","id":864},{"name":"Cutiefly","id":742},{"name":"Cyclizar","id":967},{"name":"Cyndaquil","id":155},{"name":"Dachsbun","id":927},{"name":"Darkrai","id":491},{"name":"Darmanitan","id":555},{"name":"Dartrix","id":723},{"name":"Darumaka","id":554},{"name":"Darumaka Galar","id":10176},{"name":"Decidueye","id":724},{"name":"Decidueye Hisui","id":10244},{"name":"Dedenne","id":702},{"name":"Deerling","id":585},{"name":"Deino","id":633},{"name":"Delcatty","id":301},{"name":"Delibird","id":225},{"name":"Delphox","id":655},{"name":"Deoxys","id":386},{"name":"Deoxys Attack","id":10001},{"name":"Deoxys Defense","id":10002},{"name":"Deoxys Speed","id":10003},{"name":"Dewgong","id":87},{"name":"Dewott","id":502},{"name":"Dewpider","id":751},{"name":"Dhelmise","id":781},{"name":"Dialga","id":483},{"name":"Dialga Origin","id":10245},{"name":"Diancie","id":719},{"name":"Diggersby","id":660},{"name":"Diglett","id":50},{"name":"Diglett Alola","id":10105},{"name":"Ditto","id":132},{"name":"Dodrio","id":85},{"name":"Doduo","id":84},{"name":"Dolliv","id":929},{"name":"Dondozo","id":977},{"name":"Donphan","id":232},{"name":"Dottler","id":825},{"name":"Doublade","id":680},{"name":"Dracovish","id":882},{"name":"Dracozolt","id":880},{"name":"Dragalge","id":691},{"name":"Dragapult","id":887},{"name":"Dragonair","id":148},{"name":"Dragonite","id":149},{"name":"Drakloak","id":886},{"name":"Drampa","id":780},{"name":"Drapion","id":452},{"name":"Dratini","id":147},{"name":"Drednaw","id":834},{"name":"Dreepy","id":885},{"name":"Drifblim","id":426},{"name":"Drifloon","id":425},{"name":"Drilbur","id":529},{"name":"Drizzile","id":817},{"name":"Drowzee","id":96},{"name":"Druddigon","id":621},{"name":"Dubwool","id":832},{"name":"Ducklett","id":580},{"name":"Dudunsparce","id":982},{"name":"Dudunsparce Three Segment","id":10255},{"name":"Dugtrio","id":51},{"name":"Dugtrio Alola","id":10106},{"name":"Dunsparce","id":206},{"name":"Duosion","id":578},{"name":"Duraludon","id":884},{"name":"Durant","id":632},{"name":"Dusclops","id":356},{"name":"Dusknoir","id":477},{"name":"Duskull","id":355},{"name":"Dustox","id":269},{"name":"Dwebble","id":557},{"name":"Eelektrik","id":603},{"name":"Eelektross","id":604},{"name":"Eevee","id":133},{"name":"Eevee Starter","id":10159},{"name":"Eiscue","id":875},{"name":"Eiscue Noice","id":10185},{"name":"Ekans","id":23},{"name":"Eldegoss","id":830},{"name":"Electabuzz","id":125},{"name":"Electivire","id":466},{"name":"Electrike","id":309},{"name":"Electrode","id":101},{"name":"Electrode Hisui","id":10232},{"name":"Elekid","id":239},{"name":"Elgyem","id":605},{"name":"Emboar","id":500},{"name":"Emolga","id":587},{"name":"Empoleon","id":395},{"name":"Enamorus","id":905},{"name":"Enamorus Therian","id":10249},{"name":"Entei","id":244},{"name":"Escavalier","id":589},{"name":"Espathra","id":956},{"name":"Espeon","id":196},{"name":"Espurr","id":677},{"name":"Eternatus","id":890},{"name":"Eternatus Eternamax","id":10190},{"name":"Excadrill","id":530},{"name":"Exeggcute","id":102},{"name":"Exeggutor","id":103},{"name":"Exeggutor Alola","id":10114},{"name":"Exploud","id":295},{"name":"Falinks","id":870},{"name":"Farfetch’d","id":83},{"name":"Farfetch’d Galar","id":10166},{"name":"Farigiraf","id":981},{"name":"Fearow","id":22},{"name":"Feebas","id":349},{"name":"Fennekin","id":653},{"name":"Feraligatr","id":160},{"name":"Ferroseed","id":597},{"name":"Ferrothorn","id":598},{"name":"Fidough","id":926},{"name":"Finizen","id":963},{"name":"Finneon","id":456},{"name":"Flaaffy","id":180},{"name":"Flabébé","id":669},{"name":"Flamigo","id":973},{"name":"Flapple","id":841},{"name":"Flareon","id":136},{"name":"Fletchinder","id":662},{"name":"Fletchling","id":661},{"name":"Flittle","id":955},{"name":"Floatzel","id":419},{"name":"Floette","id":670},{"name":"Floragato","id":907},{"name":"Florges","id":671},{"name":"Flutter Mane","id":987},{"name":"Flygon","id":330},{"name":"Fomantis","id":753},{"name":"Foongus","id":590},{"name":"Forretress","id":205},{"name":"Fraxure","id":611},{"name":"Frigibax","id":996},{"name":"Frillish","id":592},{"name":"Froakie","id":656},{"name":"Frogadier","id":657},{"name":"Froslass","id":478},{"name":"Frosmoth","id":873},{"name":"Fuecoco","id":909},{"name":"Furfrou","id":676},{"name":"Furret","id":162},{"name":"Gabite","id":444},{"name":"Gallade","id":475},{"name":"Galvantula","id":596},{"name":"Garbodor","id":569},{"name":"Garchomp","id":445},{"name":"Gardevoir","id":282},{"name":"Garganacl","id":934},{"name":"Gastly","id":92},{"name":"Gastrodon","id":423},{"name":"Genesect","id":649},{"name":"Gengar","id":94},{"name":"Geodude","id":74},{"name":"Geodude Alola","id":10109},{"name":"Gholdengo","id":1000},{"name":"Gible","id":443},{"name":"Gigalith","id":526},{"name":"Gimmighoul","id":999},{"name":"Gimmighoul Roaming","id":10263},{"name":"Girafarig","id":203},{"name":"Giratina","id":487},{"name":"Giratina Origin","id":10007},{"name":"Glaceon","id":471},{"name":"Glalie","id":362},{"name":"Glameow","id":431},{"name":"Glastrier","id":896},{"name":"Gligar","id":207},{"name":"Glimmet","id":969},{"name":"Glimmora","id":970},{"name":"Gliscor","id":472},{"name":"Gloom","id":44},{"name":"Gogoat","id":673},{"name":"Golbat","id":42},{"name":"Goldeen","id":118},{"name":"Golduck","id":55},{"name":"Golem","id":76},{"name":"Golem Alola","id":10111},{"name":"Golett","id":622},{"name":"Golisopod","id":768},{"name":"Golurk","id":623},{"name":"Goodra","id":706},{"name":"Goodra Hisui","id":10242},{"name":"Goomy","id":704},{"name":"Gorebyss","id":368},{"name":"Gossifleur","id":829},{"name":"Gothita","id":574},{"name":"Gothitelle","id":576},{"name":"Gothorita","id":575},{"name":"Gourgeist","id":711},{"name":"Gourgeist Large","id":10031},{"name":"Gourgeist Small","id":10030},{"name":"Gourgeist Super","id":10032},{"name":"Grafaiai","id":945},{"name":"Granbull","id":210},{"name":"Grapploct","id":853},{"name":"Graveler","id":75},{"name":"Graveler Alola","id":10110},{"name":"Great Tusk","id":984},{"name":"Greavard","id":971},{"name":"Greedent","id":820},{"name":"Greninja","id":658},{"name":"Greninja Ash","id":10117},{"name":"Grimer","id":88},{"name":"Grimer Alola","id":10112},{"name":"Grimmsnarl","id":861},{"name":"Grookey","id":810},{"name":"Grotle","id":388},{"name":"Groudon","id":383},{"name":"Groudon Primal","id":10078},{"name":"Grovyle","id":253},{"name":"Growlithe","id":58},{"name":"Growlithe Hisui","id":10229},{"name":"Grubbin","id":736},{"name":"Grumpig","id":326},{"name":"Gulpin","id":316},{"name":"Gumshoos","id":735},{"name":"Gurdurr","id":533},{"name":"Guzzlord","id":799},{"name":"Gyarados","id":130},{"name":"Hakamo-o","id":783},{"name":"Happiny","id":440},{"name":"Hariyama","id":297},{"name":"Hatenna","id":856},{"name":"Hatterene","id":858},{"name":"Hattrem","id":857},{"name":"Haunter","id":93},{"name":"Hawlucha","id":701},{"name":"Haxorus","id":612},{"name":"Heatmor","id":631},{"name":"Heatran","id":485},{"name":"Heliolisk","id":695},{"name":"Helioptile","id":694},{"name":"Heracross","id":214},{"name":"Herdier","id":507},{"name":"Hippopotas","id":449},{"name":"Hippowdon","id":450},{"name":"Hitmonchan","id":107},{"name":"Hitmonlee","id":106},{"name":"Hitmontop","id":237},{"name":"Ho Oh","id":250},{"name":"Honchkrow","id":430},{"name":"Honedge","id":679},{"name":"Hoopa","id":720},{"name":"Hoopa Unbound","id":10086},{"name":"Hoothoot","id":163},{"name":"Hoppip","id":187},{"name":"Horsea","id":116},{"name":"Houndoom","id":229},{"name":"Houndour","id":228},{"name":"Houndstone","id":972},{"name":"Huntail","id":367},{"name":"Hydreigon","id":635},{"name":"Hypno","id":97},{"name":"Igglybuff","id":174},{"name":"Illumise","id":314},{"name":"Impidimp","id":859},{"name":"Incineroar","id":727},{"name":"Indeedee","id":876},{"name":"Infernape","id":392},{"name":"Inkay","id":686},{"name":"Inteleon","id":818},{"name":"Iron Bundle","id":991},{"name":"Iron Hands","id":992},{"name":"Iron Jugulis","id":993},{"name":"Iron Moth","id":994},{"name":"Iron Thorns","id":995},{"name":"Iron Treads","id":990},{"name":"Iron Valiant","id":1006},{"name":"Ivysaur","id":2},{"name":"Jangmo-o","id":782},{"name":"Jellicent","id":593},{"name":"Jigglypuff","id":39},{"name":"Jirachi","id":385},{"name":"Jolteon","id":135},{"name":"Joltik","id":595},{"name":"Jumpluff","id":189},{"name":"Jynx","id":124},{"name":"Kabuto","id":140},{"name":"Kabutops","id":141},{"name":"Kadabra","id":64},{"name":"Kakuna","id":14},{"name":"Kangaskhan","id":115},{"name":"Karrablast","id":588},{"name":"Kartana","id":798},{"name":"Kecleon","id":352},{"name":"Keldeo","id":647},{"name":"Keldeo Resolute","id":10024},{"name":"Kilowattrel","id":941},{"name":"Kingambit","id":983},{"name":"Kingdra","id":230},{"name":"Kingler","id":99},{"name":"Kirlia","id":281},{"name":"Klang","id":600},{"name":"Klawf","id":950},{"name":"Kleavor","id":900},{"name":"Klefki","id":707},{"name":"Klink","id":599},{"name":"Klinklang","id":601},{"name":"Koffing","id":109},{"name":"Komala","id":775},{"name":"Kommo-o","id":784},{"name":"Koraidon","id":1007},{"name":"Krabby","id":98},{"name":"Kricketot","id":401},{"name":"Kricketune","id":402},{"name":"Krokorok","id":552},{"name":"Krookodile","id":553},{"name":"Kubfu","id":891},{"name":"Kyogre","id":382},{"name":"Kyogre Primal","id":10077},{"name":"Kyurem","id":646},{"name":"Kyurem Black","id":10022},{"name":"Kyurem White","id":10023},{"name":"Lairon","id":305},{"name":"Lampent","id":608},{"name":"Landorus","id":645},{"name":"Landorus Therian","id":10021},{"name":"Lanturn","id":171},{"name":"Lapras","id":131},{"name":"Larvesta","id":636},{"name":"Larvitar","id":246},{"name":"Latias","id":380},{"name":"Latios","id":381},{"name":"Leafeon","id":470},{"name":"Leavanny","id":542},{"name":"Lechonk","id":915},{"name":"Ledian","id":166},{"name":"Ledyba","id":165},{"name":"Lickilicky","id":463},{"name":"Lickitung","id":108},{"name":"Liepard","id":510},{"name":"Lileep","id":345},{"name":"Lilligant","id":549},{"name":"Lilligant Hisui","id":10237},{"name":"Lillipup","id":506},{"name":"Linoone","id":264},{"name":"Linoone Galar","id":10175},{"name":"Litleo","id":667},{"name":"Litten","id":725},{"name":"Litwick","id":607},{"name":"Lokix","id":920},{"name":"Lombre","id":271},{"name":"Lopunny","id":428},{"name":"Lotad","id":270},{"name":"Loudred","id":294},{"name":"Lucario","id":448},{"name":"Ludicolo","id":272},{"name":"Lugia","id":249},{"name":"Lumineon","id":457},{"name":"Lunala","id":792},{"name":"Lunatone","id":337},{"name":"Lurantis","id":754},{"name":"Luvdisc","id":370},{"name":"Luxio","id":404},{"name":"Luxray","id":405},{"name":"Lycanroc","id":745},{"name":"Lycanroc Dusk","id":10152},{"name":"Lycanroc Midnight","id":10126},{"name":"Mabosstiff","id":943},{"name":"Machamp","id":68},{"name":"Machoke","id":67},{"name":"Machop","id":66},{"name":"Magby","id":240},{"name":"Magcargo","id":219},{"name":"Magearna","id":801},{"name":"Magikarp","id":129},{"name":"Magmar","id":126},{"name":"Magmortar","id":467},{"name":"Magnemite","id":81},{"name":"Magneton","id":82},{"name":"Magnezone","id":462},{"name":"Makuhita","id":296},{"name":"Malamar","id":687},{"name":"Mamoswine","id":473},{"name":"Manaphy","id":490},{"name":"Mandibuzz","id":630},{"name":"Manectric","id":310},{"name":"Mankey","id":56},{"name":"Mantine","id":226},{"name":"Mantyke","id":458},{"name":"Maractus","id":556},{"name":"Mareanie","id":747},{"name":"Mareep","id":179},{"name":"Marill","id":183},{"name":"Marowak","id":105},{"name":"Marowak Alola","id":10115},{"name":"Marshadow","id":802},{"name":"Marshtomp","id":259},{"name":"Maschiff","id":942},{"name":"Masquerain","id":284},{"name":"Maushold","id":925},{"name":"Mawile","id":303},{"name":"Medicham","id":308},{"name":"Meditite","id":307},{"name":"Meganium","id":154},{"name":"Melmetal","id":809},{"name":"Meloetta","id":648},{"name":"Meloetta Pirouette","id":10018},{"name":"Meltan","id":808},{"name":"Meowscarada","id":908},{"name":"Meowstic","id":678},{"name":"Meowth","id":52},{"name":"Meowth Alola","id":10107},{"name":"Meowth Galar","id":10161},{"name":"Mesprit","id":481},{"name":"Metagross","id":376},{"name":"Metang","id":375},{"name":"Metapod","id":11},{"name":"Mew","id":151},{"name":"Mewtwo","id":150},{"name":"Mienfoo","id":619},{"name":"Mienshao","id":620},{"name":"Mightyena","id":262},{"name":"Milcery","id":868},{"name":"Milotic","id":350},{"name":"Miltank","id":241},{"name":"Mime Jr.","id":439},{"name":"Mimikyu","id":778},{"name":"Minccino","id":572},{"name":"Minior","id":774},{"name":"Minun","id":312},{"name":"Miraidon","id":1008},{"name":"Misdreavus","id":200},{"name":"Mismagius","id":429},{"name":"Moltres","id":146},{"name":"Moltres Galar","id":10171},{"name":"Monferno","id":391},{"name":"Morelull","id":755},{"name":"Morgrem","id":860},{"name":"Morpeko","id":877},{"name":"Mothim","id":414},{"name":"Mr. Mime","id":122},{"name":"Mr. Mime Galar","id":10168},{"name":"Mr. Rime","id":866},{"name":"Mudbray","id":749},{"name":"Mudkip","id":258},{"name":"Mudsdale","id":750},{"name":"Muk","id":89},{"name":"Muk Alola","id":10113},{"name":"Munchlax","id":446},{"name":"Munna","id":517},{"name":"Murkrow","id":198},{"name":"Musharna","id":518},{"name":"Nacli","id":932},{"name":"Naclstack","id":933},{"name":"Naganadel","id":804},{"name":"Natu","id":177},{"name":"Necrozma","id":800},{"name":"Necrozma Ultra","id":10157},{"name":"Nickit","id":827},{"name":"Nidoking","id":34},{"name":"Nidoqueen","id":31},{"name":"Nidoran F","id":29},{"name":"Nidoran M","id":32},{"name":"Nidorina","id":30},{"name":"Nidorino","id":33},{"name":"Nihilego","id":793},{"name":"Nincada","id":290},{"name":"Ninetales","id":38},{"name":"Ninetales Alola","id":10104},{"name":"Ninjask","id":291},{"name":"Noctowl","id":164},{"name":"Noibat","id":714},{"name":"Noivern","id":715},{"name":"Nosepass","id":299},{"name":"Numel","id":322},{"name":"Nuzleaf","id":274},{"name":"Nymble","id":919},{"name":"Obstagoon","id":862},{"name":"Octillery","id":224},{"name":"Oddish","id":43},{"name":"Oinkologne","id":916},{"name":"Omanyte","id":138},{"name":"Omastar","id":139},{"name":"Onix","id":95},{"name":"Oranguru","id":765},{"name":"Orbeetle","id":826},{"name":"Oricorio","id":741},{"name":"Oricorio Pa'u","id":10124},{"name":"Oricorio Pom Pom","id":10123},{"name":"Oricorio Sensu","id":10125},{"name":"Orthworm","id":968},{"name":"Oshawott","id":501},{"name":"Overqwil","id":904},{"name":"Pachirisu","id":417},{"name":"Palafin","id":964},{"name":"Palafin Hero","id":10256},{"name":"Palkia","id":484},{"name":"Palkia Origin","id":10246},{"name":"Palossand","id":770},{"name":"Palpitoad","id":536},{"name":"Pancham","id":674},{"name":"Pangoro","id":675},{"name":"Panpour","id":515},{"name":"Pansage","id":511},{"name":"Pansear","id":513},{"name":"Paras","id":46},{"name":"Parasect","id":47},{"name":"Passimian","id":766},{"name":"Patrat","id":504},{"name":"Pawmi","id":921},{"name":"Pawmo","id":922},{"name":"Pawmot","id":923},{"name":"Pawniard","id":624},{"name":"Pelipper","id":279},{"name":"Perrserker","id":863},{"name":"Persian","id":53},{"name":"Persian Alola","id":10108},{"name":"Petilil","id":548},{"name":"Phanpy","id":231},{"name":"Phantump","id":708},{"name":"Pheromosa","id":795},{"name":"Phione","id":489},{"name":"Pichu","id":172},{"name":"Pichu Spiky eared","id":172},{"name":"Pidgeot","id":18},{"name":"Pidgeotto","id":17},{"name":"Pidgey","id":16},{"name":"Pidove","id":519},{"name":"Pignite","id":499},{"name":"Pikachu","id":25},{"name":"Pikachu Belle","id":10081},{"name":"Pikachu Cosplay","id":10085},{"name":"Pikachu Libre","id":10084},{"name":"Pikachu PhD","id":10083},{"name":"Pikachu Pop Star","id":10082},{"name":"Pikachu Rock Star","id":10080},{"name":"Pikachu Starter","id":10158},{"name":"Pikipek","id":731},{"name":"Piloswine","id":221},{"name":"Pincurchin","id":871},{"name":"Pineco","id":204},{"name":"Pinsir","id":127},{"name":"Piplup","id":393},{"name":"Plusle","id":311},{"name":"Poipole","id":803},{"name":"Politoed","id":186},{"name":"Poliwag","id":60},{"name":"Poliwhirl","id":61},{"name":"Poliwrath","id":62},{"name":"Polteageist","id":855},{"name":"Ponyta","id":77},{"name":"Ponyta Galar","id":10162},{"name":"Poochyena","id":261},{"name":"Popplio","id":728},{"name":"Porygon","id":137},{"name":"Porygon Z","id":474},{"name":"Porygon2","id":233},{"name":"Primarina","id":730},{"name":"Primeape","id":57},{"name":"Prinplup","id":394},{"name":"Probopass","id":476},{"name":"Psyduck","id":54},{"name":"Pumpkaboo","id":710},{"name":"Pumpkaboo Large","id":10028},{"name":"Pumpkaboo Small","id":10027},{"name":"Pumpkaboo Super","id":10029},{"name":"Pupitar","id":247},{"name":"Purrloin","id":509},{"name":"Purugly","id":432},{"name":"Pyroar","id":668},{"name":"Pyukumuku","id":771},{"name":"Quagsire","id":195},{"name":"Quaquaval","id":914},{"name":"Quaxly","id":912},{"name":"Quaxwell","id":913},{"name":"Quilava","id":156},{"name":"Quilladin","id":651},{"name":"Qwilfish","id":211},{"name":"Qwilfish Hisui","id":10234},{"name":"Raboot","id":814},{"name":"Rabsca","id":954},{"name":"Raichu","id":26},{"name":"Raichu Alola","id":10100},{"name":"Raikou","id":243},{"name":"Ralts","id":280},{"name":"Rampardos","id":409},{"name":"Rapidash","id":78},{"name":"Rapidash Galar","id":10163},{"name":"Raticate","id":20},{"name":"Raticate Alola","id":10092},{"name":"Rattata","id":19},{"name":"Rattata Alola","id":10091},{"name":"Rayquaza","id":384},{"name":"Regice","id":378},{"name":"Regidrago","id":895},{"name":"Regieleki","id":894},{"name":"Regigigas","id":486},{"name":"Regirock","id":377},{"name":"Registeel","id":379},{"name":"Relicanth","id":369},{"name":"Rellor","id":953},{"name":"Remoraid","id":223},{"name":"Reshiram","id":643},{"name":"Reuniclus","id":579},{"name":"Revavroom","id":966},{"name":"Rhydon","id":112},{"name":"Rhyhorn","id":111},{"name":"Rhyperior","id":464},{"name":"Ribombee","id":743},{"name":"Rillaboom","id":812},{"name":"Riolu","id":447},{"name":"Roaring Moon","id":1005},{"name":"Rockruff","id":744},{"name":"Roggenrola","id":524},{"name":"Rolycoly","id":837},{"name":"Rookidee","id":821},{"name":"Roselia","id":315},{"name":"Roserade","id":407},{"name":"Rotom","id":479},{"name":"Rotom Fan","id":10011},{"name":"Rotom Frost","id":10010},{"name":"Rotom Heat","id":10008},{"name":"Rotom Mow","id":10012},{"name":"Rotom Wash","id":10009},{"name":"Rowlet","id":722},{"name":"Rufflet","id":627},{"name":"Runerigus","id":867},{"name":"Sableye","id":302},{"name":"Salamence","id":373},{"name":"Salandit","id":757},{"name":"Salazzle","id":758},{"name":"Samurott","id":503},{"name":"Samurott Hisui","id":10236},{"name":"Sandaconda","id":844},{"name":"Sandile","id":551},{"name":"Sandshrew","id":27},{"name":"Sandshrew Alola","id":10101},{"name":"Sandslash","id":28},{"name":"Sandslash Alola","id":10102},{"name":"Sandygast","id":769},{"name":"Sawk","id":539},{"name":"Sawsbuck","id":586},{"name":"Scatterbug","id":664},{"name":"Sceptile","id":254},{"name":"Scizor","id":212},{"name":"Scolipede","id":545},{"name":"Scorbunny","id":813},{"name":"Scovillain","id":952},{"name":"Scrafty","id":560},{"name":"Scraggy","id":559},{"name":"Scream Tail","id":985},{"name":"Scyther","id":123},{"name":"Seadra","id":117},{"name":"Seaking","id":119},{"name":"Sealeo","id":364},{"name":"Seedot","id":273},{"name":"Seel","id":86},{"name":"Seismitoad","id":537},{"name":"Sentret","id":161},{"name":"Serperior","id":497},{"name":"Servine","id":496},{"name":"Seviper","id":336},{"name":"Sewaddle","id":540},{"name":"Sharpedo","id":319},{"name":"Shaymin","id":492},{"name":"Shaymin Sky","id":10006},{"name":"Shedinja","id":292},{"name":"Shelgon","id":372},{"name":"Shellder","id":90},{"name":"Shellos","id":422},{"name":"Shelmet","id":616},{"name":"Shieldon","id":410},{"name":"Shiftry","id":275},{"name":"Shiinotic","id":756},{"name":"Shinx","id":403},{"name":"Shroodle","id":944},{"name":"Shroomish","id":285},{"name":"Shuckle","id":213},{"name":"Shuppet","id":353},{"name":"Sigilyph","id":561},{"name":"Silcoon","id":266},{"name":"Silicobra","id":843},{"name":"Silvally","id":773},{"name":"Silvally Bug","id":773},{"name":"Silvally Dark","id":773},{"name":"Silvally Dragon","id":773},{"name":"Silvally Electric","id":773},{"name":"Silvally Fairy","id":773},{"name":"Silvally Fighting","id":773},{"name":"Silvally Fire","id":773},{"name":"Silvally Flying","id":773},{"name":"Silvally Ghost","id":773},{"name":"Silvally Grass","id":773},{"name":"Silvally Ground","id":773},{"name":"Silvally Ice","id":773},{"name":"Silvally Poison","id":773},{"name":"Silvally Psychic","id":773},{"name":"Silvally Rock","id":773},{"name":"Silvally Steel","id":773},{"name":"Silvally Water","id":773},{"name":"Simipour","id":516},{"name":"Simisage","id":512},{"name":"Simisear","id":514},{"name":"Sinistea","id":854},{"name":"Sirfetch’d","id":865},{"name":"Sizzlipede","id":850},{"name":"Skarmory","id":227},{"name":"Skeledirge","id":911},{"name":"Skiddo","id":672},{"name":"Skiploom","id":188},{"name":"Skitty","id":300},{"name":"Skorupi","id":451},{"name":"Skrelp","id":690},{"name":"Skuntank","id":435},{"name":"Skwovet","id":819},{"name":"Slaking","id":289},{"name":"Slakoth","id":287},{"name":"Sliggoo","id":705},{"name":"Sliggoo Hisui","id":10241},{"name":"Slither Wing","id":988},{"name":"Slowbro","id":80},{"name":"Slowbro Galar","id":10165},{"name":"Slowking","id":199},{"name":"Slowking Galar","id":10172},{"name":"Slowpoke","id":79},{"name":"Slowpoke Galar","id":10164},{"name":"Slugma","id":218},{"name":"Slurpuff","id":685},{"name":"Smeargle","id":235},{"name":"Smoliv","id":928},{"name":"Smoochum","id":238},{"name":"Sneasel","id":215},{"name":"Sneasel Hisui","id":10235},{"name":"Sneasler","id":903},{"name":"Snivy","id":495},{"name":"Snom","id":872},{"name":"Snorlax","id":143},{"name":"Snorunt","id":361},{"name":"Snover","id":459},{"name":"Snubbull","id":209},{"name":"Sobble","id":816},{"name":"Solgaleo","id":791},{"name":"Solosis","id":577},{"name":"Solrock","id":338},{"name":"Spearow","id":21},{"name":"Spectrier","id":897},{"name":"Spewpa","id":665},{"name":"Spheal","id":363},{"name":"Spidops","id":918},{"name":"Spinarak","id":167},{"name":"Spinda","id":327},{"name":"Spiritomb","id":442},{"name":"Spoink","id":325},{"name":"Sprigatito","id":906},{"name":"Spritzee","id":682},{"name":"Squawkabilly","id":931},{"name":"Squirtle","id":7},{"name":"Stakataka","id":805},{"name":"Stantler","id":234},{"name":"Staraptor","id":398},{"name":"Staravia","id":397},{"name":"Starly","id":396},{"name":"Starmie","id":121},{"name":"Staryu","id":120},{"name":"Steelix","id":208},{"name":"Steenee","id":762},{"name":"Stonjourner","id":874},{"name":"Stoutland","id":508},{"name":"Stufful","id":759},{"name":"Stunfisk","id":618},{"name":"Stunfisk Galar","id":10180},{"name":"Stunky","id":434},{"name":"Sudowoodo","id":185},{"name":"Suicune","id":245},{"name":"Sunflora","id":192},{"name":"Sunkern","id":191},{"name":"Surskit","id":283},{"name":"Swablu","id":333},{"name":"Swadloon","id":541},{"name":"Swalot","id":317},{"name":"Swampert","id":260},{"name":"Swanna","id":581},{"name":"Swellow","id":277},{"name":"Swinub","id":220},{"name":"Swirlix","id":684},{"name":"Swoobat","id":528},{"name":"Sylveon","id":700},{"name":"Tadbulb","id":938},{"name":"Taillow","id":276},{"name":"Talonflame","id":663},{"name":"Tandemaus","id":924},{"name":"Tangela","id":114},{"name":"Tangrowth","id":465},{"name":"Tapu Bulu","id":787},{"name":"Tapu Fini","id":788},{"name":"Tapu Koko","id":785},{"name":"Tapu Lele","id":786},{"name":"Tarountula","id":917},{"name":"Tatsugiri","id":978},{"name":"Tauros","id":128},{"name":"Teddiursa","id":216},{"name":"Tentacool","id":72},{"name":"Tentacruel","id":73},{"name":"Tepig","id":498},{"name":"Terrakion","id":639},{"name":"Thievul","id":828},{"name":"Throh","id":538},{"name":"Thundurus","id":642},{"name":"Thundurus Therian","id":10020},{"name":"Thwackey","id":811},{"name":"Timburr","id":532},{"name":"Ting Lu","id":1003},{"name":"Tinkatink","id":957},{"name":"Tinkaton","id":959},{"name":"Tinkatuff","id":958},{"name":"Tirtouga","id":564},{"name":"Toedscool","id":948},{"name":"Toedscruel","id":949},{"name":"Togedemaru","id":777},{"name":"Togekiss","id":468},{"name":"Togepi","id":175},{"name":"Togetic","id":176},{"name":"Torchic","id":255},{"name":"Torkoal","id":324},{"name":"Tornadus","id":641},{"name":"Tornadus Therian","id":10019},{"name":"Torracat","id":726},{"name":"Torterra","id":389},{"name":"Totodile","id":158},{"name":"Toucannon","id":733},{"name":"Toxapex","id":748},{"name":"Toxel","id":848},{"name":"Toxicroak","id":454},{"name":"Toxtricity","id":849},{"name":"Toxtricity Low Key","id":10184},{"name":"Tranquill","id":520},{"name":"Trapinch","id":328},{"name":"Treecko","id":252},{"name":"Trevenant","id":709},{"name":"Tropius","id":357},{"name":"Trubbish","id":568},{"name":"Trumbeak","id":732},{"name":"Tsareena","id":763},{"name":"Turtonator","id":776},{"name":"Turtwig","id":387},{"name":"Tympole","id":535},{"name":"Tynamo","id":602},{"name":"Type: Null","id":772},{"name":"Typhlosion","id":157},{"name":"Typhlosion Hisui","id":10233},{"name":"Tyranitar","id":248},{"name":"Tyrantrum","id":697},{"name":"Tyrogue","id":236},{"name":"Tyrunt","id":696},{"name":"Umbreon","id":197},{"name":"Unfezant","id":521},{"name":"Unown","id":201},{"name":"Ursaluna","id":901},{"name":"Ursaring","id":217},{"name":"Urshifu","id":892},{"name":"Urshifu Rapid Strike","id":10191},{"name":"Uxie","id":480},{"name":"Vanillish","id":583},{"name":"Vanillite","id":582},{"name":"Vanilluxe","id":584},{"name":"Vaporeon","id":134},{"name":"Varoom","id":965},{"name":"Veluza","id":976},{"name":"Venipede","id":543},{"name":"Venomoth","id":49},{"name":"Venonat","id":48},{"name":"Venusaur","id":3},{"name":"Vespiquen","id":416},{"name":"Vibrava","id":329},{"name":"Victini","id":494},{"name":"Victreebel","id":71},{"name":"Vigoroth","id":288},{"name":"Vikavolt","id":738},{"name":"Vileplume","id":45},{"name":"Virizion","id":640},{"name":"Vivillon","id":666},{"name":"Volbeat","id":313},{"name":"Volcanion","id":721},{"name":"Volcarona","id":637},{"name":"Voltorb","id":100},{"name":"Voltorb Hisui","id":10231},{"name":"Vullaby","id":629},{"name":"Vulpix","id":37},{"name":"Vulpix Alola","id":10103},{"name":"Wailmer","id":320},{"name":"Wailord","id":321},{"name":"Walrein","id":365},{"name":"Wartortle","id":8},{"name":"Watchog","id":505},{"name":"Wattrel","id":940},{"name":"Weavile","id":461},{"name":"Weedle","id":13},{"name":"Weepinbell","id":70},{"name":"Weezing","id":110},{"name":"Weezing Galar","id":10167},{"name":"Whimsicott","id":547},{"name":"Whirlipede","id":544},{"name":"Whiscash","id":340},{"name":"Whismur","id":293},{"name":"Wigglytuff","id":40},{"name":"Wiglett","id":960},{"name":"Wimpod","id":767},{"name":"Wingull","id":278},{"name":"Wishiwashi","id":746},{"name":"Wishiwashi School","id":10127},{"name":"Wo Chien","id":1001},{"name":"Wobbuffet","id":202},{"name":"Woobat","id":527},{"name":"Wooloo","id":831},{"name":"Wooper","id":194},{"name":"Wooper Paldea","id":10253},{"name":"Wormadam","id":413},{"name":"Wormadam Sandy","id":10004},{"name":"Wormadam Trash","id":10005},{"name":"Wugtrio","id":961},{"name":"Wurmple","id":265},{"name":"Wynaut","id":360},{"name":"Wyrdeer","id":899},{"name":"Xatu","id":178},{"name":"Xerneas","id":716},{"name":"Xerneas Neutral","id":716},{"name":"Xurkitree","id":796},{"name":"Yamask","id":562},{"name":"Yamask Galar","id":10179},{"name":"Yamper","id":835},{"name":"Yanma","id":193},{"name":"Yanmega","id":469},{"name":"Yungoos","id":734},{"name":"Yveltal","id":717},{"name":"Zacian","id":888},{"name":"Zacian Crowned","id":10188},{"name":"Zamazenta","id":889},{"name":"Zamazenta Crowned","id":10189},{"name":"Zangoose","id":335},{"name":"Zapdos","id":145},{"name":"Zapdos Galar","id":10170},{"name":"Zarude","id":893},{"name":"Zebstrika","id":523},{"name":"Zekrom","id":644},{"name":"Zeraora","id":807},{"name":"Zigzagoon","id":263},{"name":"Zigzagoon Galar","id":10174},{"name":"Zoroark","id":571},{"name":"Zoroark Hisui","id":10239},{"name":"Zorua","id":570},{"name":"Zorua Hisui","id":10238},{"name":"Zubat","id":41},{"name":"Zweilous","id":634},{"name":"Zygarde","id":718},{"name":"Zygarde 10%","id":10181},{"name":"Zygarde Complete","id":10120}]